{
  "Menu": [


    {
      "Category": "News",
      "Name": "ARY News",
      "Country": "PK",
      "URL": "https://youtu.be/vYTfRrA0rBw",
      "Image": "https://img.youtube.com/vi/vYTfRrA0rBw/mqdefault.jpg"
    },


    {
      "Category": "News",
      "Name": "Dunya News",
      "Country": "PK",
      "URL": "https://www.youtube.com/watch?v=GlHSFtTFfJE",
      "Image": "https://img.youtube.com/vi/GlHSFtTFfJE/mqdefault.jpg"
    },

    {
      "Category": "News",
      "Name": "Geo News",
      "Country": "PK",
      "URL": "https://youtu.be/_FwympjOSNE",
      "Image": "https://img.youtube.com/vi/_FwympjOSNE/mqdefault.jpg"
    },
    {
      "Category": "News",
      "Name": "ABC News Live",
      "Country": "US",
      "URL": "https://youtu.be/-mvUkiILTqI&mode=theatre",
      "Image": "https://img.youtube.com/vi/-mvUkiILTqI/mqdefault.jpg"
    },

    {
      "Category": "News",
      "Name": "Al Jazeera English",
      "Country": "US",
      "URL": "https://www.youtube.com/watch?v=gCNeDWCI0vo",
      "Image": "https://img.youtube.com/vi/gCNeDWCI0vo/mqdefault.jpg"
    },




    {
      "Category": "News",
      "Name": "GB News",
      "Country": "UK",
      "URL": "https://www.youtube.com/watch?v=8WX6YL9JnLw",
      "Image": "https://img.youtube.com/vi/8WX6YL9JnLw/mqdefault.jpg"
    },

    {
      "Category": "News",
      "Name": "CNA 24/7 LIVE",
      "Country": "CN",
      "URL": "https://www.youtube.com/watch?v=XWq5kBlakcQ",
      "Image": "https://img.youtube.com/vi/XWq5kBlakcQ/mqdefault.jpg"
    },
    {
      "Category": "News",
      "Name": "SAMAA News Live",
      "Country": "Unknown",
      "URL": "https://youtu.be/Nh_qJClxWec",
      "Image": "https://img.youtube.com/vi/Nh_qJClxWec/mqdefault.jpg"
    },
    {
      "Category": "News",
      "Name": "Bol News Live",
      "Country": "PK",
      "URL": "https://youtu.be/4_HJbqz3KlU",
      "Image": "https://img.youtube.com/vi/4_HJbqz3KlU/mqdefault.jpg"
    },
    {
      "Category": "News",
      "Name": "Aaj News Live",
      "Country": "PK",
      "URL": "https://youtu.be/CAz6J3B1NvM",
      "Image": "https://img.youtube.com/vi/CAz6J3B1NvM/mqdefault.jpg"
    },
    {
      "Category": "News",
      "Name": "NBC News",
      "Country": "US",
      "URL": "https://youtu.be/a_bvmBLCrcQ",
      "Image": "https://img.youtube.com/vi/a_bvmBLCrcQ/mqdefault.jpg"
    },


    {
      "Category": "News",
      "Name": "GNN News Live",
      "Country": "PK",
      "URL": "https://youtu.be/8mhPYTm3kEs",
      "Image": "https://img.youtube.com/vi/8mhPYTm3kEs/mqdefault.jpg"
    },
    {
      "Category": "News",
      "Name": "WION News Live",
      "Country": "Unknown",
      "URL": "https://www.youtube.com/watch?v=vfszY1JYbMc",
      "Image": "https://img.youtube.com/vi/vfszY1JYbMc/mqdefault.jpg"
    },
    {
      "Category": "News",
      "Name": "LiveNOW Fox Live",
      "Country": "US",
      "URL": "https://www.youtube.com/watch?v=baNySiBUP0Y",
      "Image": "https://img.youtube.com/vi/baNySiBUP0Y/mqdefault.jpg"
    },
    {
      "Category": "News",
      "Name": "Sky News Live",
      "Country": "UK",
      "URL": "https://youtu.be/YDvsBbKfLPA",
      "Image": "https://img.youtube.com/vi/YDvsBbKfLPA/mqdefault.jpg"
    },
    {
      "Category": "News",
      "Name": "CNN News",
      "Country": "US",
      "URL": "https://youtu.be/9hTxn5kOrEA",
      "Image": "https://img.youtube.com/vi/9hTxn5kOrEA/mqdefault.jpg"
    },
    {
      "Category": "News",
      "Name": "ABP News",
      "Country": "IN",
      "URL": "https://youtu.be/vMGDk0hDrGg",
      "Image": "https://img.youtube.com/vi/vMGDk0hDrGg/mqdefault.jpg"
    },
    {
      "Category": "News",
      "Name": "24 One News",
      "Country": "PK",
      "URL": "https://youtu.be/vZO0t7DtGBY",
      "Image": "https://img.youtube.com/vi/vZO0t7DtGBY/mqdefault.jpg"
    }



  ]
}
